{
    "format_version": "1.12",
    "minecraft:recipe_shaped": {
        "description": {
            "identifier": "crafting:friedapplerecipe"
        },
        "tags": [
            "crafting_table"
        ],
        "pattern": [
            " # ",
            "WAW",
            "E#E"
        ],
        "key": {
            "#": {
                "item": "minecraft:sugar"
            },
            "W": {
                "item": "minecraft:wheat"
            },
            "A": {
                "item": "minecraft:apple"
            },
            "E": {
                "item": "minecraft:egg"
            }
        },
        "result": {
            "item": "foodsplus2:friedapple",
            "count": 2
        }
    }
}